{
  "samples_local": {
    "10": {
      "temp": 11.9,
      "precip": 0.7,
      "wind": 21.8,
      "wind_dir_deg": 98.0
    },
    "12": {
      "temp": 12.8,
      "precip": 0.7,
      "wind": 22.4,
      "wind_dir_deg": 96.0
    },
    "14": {
      "temp": 13.3,
      "precip": 0.9,
      "wind": 23.4,
      "wind_dir_deg": 94.0
    },
    "16": {
      "temp": 12.8,
      "precip": 0.0,
      "wind": 22.3,
      "wind_dir_deg": 90.0
    }
  },
  "ride_temp_mean": 12.700000000000001,
  "ride_wind_mean": 22.475,
  "ride_wind_dir_deg": 94.47663232526577,
  "ride_rain_flag": 1.0,
  "tent_rain_flag": 1.0,
  "daily_precip_sum": 5.3,
  "daily_temp_mean": 11.158333333333333,
  "daily_wind_mean": 18.3625,
  "daily_wind_dir_deg": 98.68093242326722
}