{
  "samples_local": {
    "10": {
      "temp": 7.2,
      "precip": 1.6,
      "wind": 4.4,
      "wind_dir_deg": 12.0
    },
    "12": {
      "temp": 6.4,
      "precip": 4.4,
      "wind": 2.3,
      "wind_dir_deg": 331.0
    },
    "14": {
      "temp": 6.5,
      "precip": 0.9,
      "wind": 3.9,
      "wind_dir_deg": 143.0
    },
    "16": {
      "temp": 7.2,
      "precip": 1.1,
      "wind": 2.8,
      "wind_dir_deg": 165.0
    }
  },
  "ride_temp_mean": 6.825,
  "ride_wind_mean": 3.35,
  "ride_wind_dir_deg": 80.19600635436939,
  "ride_rain_flag": 1.0,
  "tent_rain_flag": 1.0,
  "daily_precip_sum": 35.300000000000004,
  "daily_temp_mean": 6.7625,
  "daily_wind_mean": 6.533333333333334,
  "daily_wind_dir_deg": 303.964945157869
}