{
  "samples_local": {
    "10": {
      "temp": 27.2,
      "precip": 0.0,
      "wind": 4.7,
      "wind_dir_deg": 293.0
    },
    "12": {
      "temp": 29.0,
      "precip": 0.0,
      "wind": 2.2,
      "wind_dir_deg": 270.0
    },
    "14": {
      "temp": 29.9,
      "precip": 0.0,
      "wind": 2.2,
      "wind_dir_deg": 171.0
    },
    "16": {
      "temp": 29.8,
      "precip": 0.0,
      "wind": 8.7,
      "wind_dir_deg": 173.0
    }
  },
  "ride_temp_mean": 28.975,
  "ride_wind_mean": 4.45,
  "ride_wind_dir_deg": 209.7222885988352,
  "ride_rain_flag": 0.0,
  "tent_rain_flag": 0.0,
  "daily_precip_sum": 0.1,
  "daily_temp_mean": 23.40833333333333,
  "daily_wind_mean": 5.954166666666667,
  "daily_wind_dir_deg": 265.1825003411274
}