{
  "samples_local": {
    "10": {
      "temp": 20.0,
      "precip": 0.0,
      "wind": 13.1,
      "wind_dir_deg": 8.0
    },
    "12": {
      "temp": 22.8,
      "precip": 0.0,
      "wind": 19.1,
      "wind_dir_deg": 39.0
    },
    "14": {
      "temp": 22.9,
      "precip": 0.1,
      "wind": 17.7,
      "wind_dir_deg": 47.0
    },
    "16": {
      "temp": 21.6,
      "precip": 0.7,
      "wind": 18.2,
      "wind_dir_deg": 72.0
    }
  },
  "ride_temp_mean": 21.825,
  "ride_wind_mean": 17.025,
  "ride_wind_dir_deg": 44.095899127772554,
  "ride_rain_flag": 1.0,
  "tent_rain_flag": 1.0,
  "daily_precip_sum": 1.2,
  "daily_temp_mean": 18.641666666666666,
  "daily_wind_mean": 13.808333333333332,
  "daily_wind_dir_deg": 1.294449447920897
}