{
  "samples_local": {
    "10": {
      "temp": 1.9,
      "precip": 0.0,
      "wind": 13.4,
      "wind_dir_deg": 59.0
    },
    "12": {
      "temp": 1.9,
      "precip": 0.3,
      "wind": 17.8,
      "wind_dir_deg": 82.0
    },
    "14": {
      "temp": 4.2,
      "precip": 0.1,
      "wind": 15.5,
      "wind_dir_deg": 102.0
    },
    "16": {
      "temp": 4.2,
      "precip": 0.0,
      "wind": 13.8,
      "wind_dir_deg": 123.0
    }
  },
  "ride_temp_mean": 3.05,
  "ride_wind_mean": 15.125,
  "ride_wind_dir_deg": 91.39484137374745,
  "ride_rain_flag": 1.0,
  "tent_rain_flag": 1.0,
  "daily_precip_sum": 2.9,
  "daily_temp_mean": 0.85,
  "daily_wind_mean": 10.191666666666666,
  "daily_wind_dir_deg": 99.27003728648378
}