{
  "samples_local": {
    "10": {
      "temp": 9.3,
      "precip": 0.0,
      "wind": 8.4,
      "wind_dir_deg": 191.0
    },
    "12": {
      "temp": 10.1,
      "precip": 0.0,
      "wind": 9.6,
      "wind_dir_deg": 193.0
    },
    "14": {
      "temp": 11.9,
      "precip": 0.1,
      "wind": 11.2,
      "wind_dir_deg": 195.0
    },
    "16": {
      "temp": 12.9,
      "precip": 0.0,
      "wind": 11.7,
      "wind_dir_deg": 197.0
    }
  },
  "ride_temp_mean": 11.05,
  "ride_wind_mean": 10.225,
  "ride_wind_dir_deg": 194.28126998744898,
  "ride_rain_flag": 0.0,
  "tent_rain_flag": 0.0,
  "daily_precip_sum": 0.2,
  "daily_temp_mean": 8.620833333333334,
  "daily_wind_mean": 8.495833333333334,
  "daily_wind_dir_deg": 183.97421681040097
}