{
  "samples_local": {
    "10": {
      "temp": 13.0,
      "precip": 0.0,
      "wind": 3.5,
      "wind_dir_deg": 192.0
    },
    "12": {
      "temp": 16.4,
      "precip": 0.0,
      "wind": 6.9,
      "wind_dir_deg": 135.0
    },
    "14": {
      "temp": 17.2,
      "precip": 1.5,
      "wind": 12.0,
      "wind_dir_deg": 112.0
    },
    "16": {
      "temp": 16.8,
      "precip": 0.0,
      "wind": 14.3,
      "wind_dir_deg": 111.0
    }
  },
  "ride_temp_mean": 15.85,
  "ride_wind_mean": 9.175,
  "ride_wind_dir_deg": 122.0487536053995,
  "ride_rain_flag": 1.0,
  "tent_rain_flag": 1.0,
  "daily_precip_sum": 2.0,
  "daily_temp_mean": 10.095833333333333,
  "daily_wind_mean": 6.916666666666667,
  "daily_wind_dir_deg": 154.9656261778938
}