{
  "samples_local": {
    "10": {
      "temp": 13.6,
      "precip": 0.5,
      "wind": 4.0,
      "wind_dir_deg": 265.0
    },
    "12": {
      "temp": 14.7,
      "precip": 1.2,
      "wind": 9.1,
      "wind_dir_deg": 279.0
    },
    "14": {
      "temp": 14.4,
      "precip": 0.1,
      "wind": 6.6,
      "wind_dir_deg": 296.0
    },
    "16": {
      "temp": 15.7,
      "precip": 0.0,
      "wind": 9.7,
      "wind_dir_deg": 301.0
    }
  },
  "ride_temp_mean": 14.6,
  "ride_wind_mean": 7.35,
  "ride_wind_dir_deg": 288.22810421871475,
  "ride_rain_flag": 1.0,
  "tent_rain_flag": 1.0,
  "daily_precip_sum": 3.2,
  "daily_temp_mean": 12.166666666666666,
  "daily_wind_mean": 6.204166666666667,
  "daily_wind_dir_deg": 298.7394060637574
}