{
  "samples_local": {
    "10": {
      "temp": 18.0,
      "precip": 0.1,
      "wind": 12.4,
      "wind_dir_deg": 123.0
    },
    "12": {
      "temp": 19.5,
      "precip": 0.1,
      "wind": 12.7,
      "wind_dir_deg": 126.0
    },
    "14": {
      "temp": 20.2,
      "precip": 0.0,
      "wind": 15.4,
      "wind_dir_deg": 111.0
    },
    "16": {
      "temp": 19.0,
      "precip": 0.0,
      "wind": 16.0,
      "wind_dir_deg": 102.0
    }
  },
  "ride_temp_mean": 19.175,
  "ride_wind_mean": 14.125,
  "ride_wind_dir_deg": 114.46052940715902,
  "ride_rain_flag": 0.0,
  "tent_rain_flag": 1.0,
  "daily_precip_sum": 1.0,
  "daily_temp_mean": 14.658333333333333,
  "daily_wind_mean": 8.5,
  "daily_wind_dir_deg": 112.14696071835783
}