{
  "samples_local": {
    "10": {
      "temp": -2.4,
      "precip": 0.4,
      "wind": 7.5,
      "wind_dir_deg": 250.0
    },
    "12": {
      "temp": -1.2,
      "precip": 0.2,
      "wind": 7.3,
      "wind_dir_deg": 254.0
    },
    "14": {
      "temp": -2.3,
      "precip": 0.1,
      "wind": 8.8,
      "wind_dir_deg": 258.0
    },
    "16": {
      "temp": -2.7,
      "precip": 0.0,
      "wind": 7.9,
      "wind_dir_deg": 254.0
    }
  },
  "ride_temp_mean": -2.15,
  "ride_wind_mean": 7.875,
  "ride_wind_dir_deg": 254.16515302139163,
  "ride_rain_flag": 1.0,
  "tent_rain_flag": 1.0,
  "daily_precip_sum": 16.4,
  "daily_temp_mean": -3.2416666666666667,
  "daily_wind_mean": 5.416666666666667,
  "daily_wind_dir_deg": 250.0727406890959
}