{
  "samples_local": {
    "10": {
      "temp": 1.2,
      "precip": 0.0,
      "wind": 5.1,
      "wind_dir_deg": 84.0
    },
    "12": {
      "temp": 3.5,
      "precip": 0.0,
      "wind": 7.0,
      "wind_dir_deg": 102.0
    },
    "14": {
      "temp": 4.3,
      "precip": 0.1,
      "wind": 9.4,
      "wind_dir_deg": 91.0
    },
    "16": {
      "temp": 3.6,
      "precip": 0.0,
      "wind": 7.6,
      "wind_dir_deg": 68.0
    }
  },
  "ride_temp_mean": 3.15,
  "ride_wind_mean": 7.275,
  "ride_wind_dir_deg": 86.44800402803253,
  "ride_rain_flag": 0.0,
  "tent_rain_flag": 1.0,
  "daily_precip_sum": 0.4,
  "daily_temp_mean": 1.5541666666666665,
  "daily_wind_mean": 7.704166666666667,
  "daily_wind_dir_deg": 95.1317686712132
}