{
  "samples_local": {
    "10": {
      "temp": 6.4,
      "precip": 0.0,
      "wind": 19.9,
      "wind_dir_deg": 347.0
    },
    "12": {
      "temp": 8.8,
      "precip": 0.0,
      "wind": 19.3,
      "wind_dir_deg": 349.0
    },
    "14": {
      "temp": 11.9,
      "precip": 0.0,
      "wind": 19.5,
      "wind_dir_deg": 12.0
    },
    "16": {
      "temp": 10.7,
      "precip": 0.0,
      "wind": 18.4,
      "wind_dir_deg": 354.0
    }
  },
  "ride_temp_mean": 9.45,
  "ride_wind_mean": 19.275,
  "ride_wind_dir_deg": 355.4475038506609,
  "ride_rain_flag": 0.0,
  "tent_rain_flag": 0.0,
  "daily_precip_sum": 0.0,
  "daily_temp_mean": 5.425,
  "daily_wind_mean": 18.454166666666666,
  "daily_wind_dir_deg": 338.5382590782865
}