{
  "samples_local": {
    "10": {
      "temp": 7.0,
      "precip": 0.0,
      "wind": 4.8,
      "wind_dir_deg": 225.0
    },
    "12": {
      "temp": 10.6,
      "precip": 0.0,
      "wind": 6.5,
      "wind_dir_deg": 222.0
    },
    "14": {
      "temp": 11.9,
      "precip": 0.0,
      "wind": 9.3,
      "wind_dir_deg": 230.0
    },
    "16": {
      "temp": 11.8,
      "precip": 0.0,
      "wind": 8.4,
      "wind_dir_deg": 233.0
    }
  },
  "ride_temp_mean": 10.325,
  "ride_wind_mean": 7.25,
  "ride_wind_dir_deg": 228.2496771697776,
  "ride_rain_flag": 0.0,
  "tent_rain_flag": 0.0,
  "daily_precip_sum": 0.0,
  "daily_temp_mean": 6.8500000000000005,
  "daily_wind_mean": 5.020833333333333,
  "daily_wind_dir_deg": 225.2218819463086
}