{
  "samples_local": {
    "10": {
      "temp": 14.0,
      "precip": 0.1,
      "wind": 14.2,
      "wind_dir_deg": 7.0
    },
    "12": {
      "temp": 15.8,
      "precip": 0.0,
      "wind": 17.3,
      "wind_dir_deg": 12.0
    },
    "14": {
      "temp": 17.0,
      "precip": 0.0,
      "wind": 20.2,
      "wind_dir_deg": 24.0
    },
    "16": {
      "temp": 19.7,
      "precip": 0.0,
      "wind": 22.4,
      "wind_dir_deg": 54.0
    }
  },
  "ride_temp_mean": 16.625,
  "ride_wind_mean": 18.525,
  "ride_wind_dir_deg": 26.81872553364741,
  "ride_rain_flag": 0.0,
  "tent_rain_flag": 1.0,
  "daily_precip_sum": 0.4,
  "daily_temp_mean": 15.424999999999999,
  "daily_wind_mean": 15.958333333333334,
  "daily_wind_dir_deg": 38.70460420703745
}