{
  "samples_local": {
    "10": {
      "temp": 10.3,
      "precip": 0.2,
      "wind": 30.3,
      "wind_dir_deg": 66.0
    },
    "12": {
      "temp": 10.5,
      "precip": 0.5,
      "wind": 33.2,
      "wind_dir_deg": 81.0
    },
    "14": {
      "temp": 10.0,
      "precip": 0.4,
      "wind": 31.7,
      "wind_dir_deg": 99.0
    },
    "16": {
      "temp": 9.3,
      "precip": 0.0,
      "wind": 29.0,
      "wind_dir_deg": 96.0
    }
  },
  "ride_temp_mean": 10.025,
  "ride_wind_mean": 31.05,
  "ride_wind_dir_deg": 85.4838330993432,
  "ride_rain_flag": 1.0,
  "tent_rain_flag": 1.0,
  "daily_precip_sum": 4.6,
  "daily_temp_mean": 8.404166666666667,
  "daily_wind_mean": 27.087500000000002,
  "daily_wind_dir_deg": 77.27595110573048
}