{
  "samples_local": {
    "10": {
      "temp": 6.1,
      "precip": 0.0,
      "wind": 13.3,
      "wind_dir_deg": 88.0
    },
    "12": {
      "temp": 8.1,
      "precip": 0.2,
      "wind": 15.4,
      "wind_dir_deg": 79.0
    },
    "14": {
      "temp": 9.8,
      "precip": 0.0,
      "wind": 17.7,
      "wind_dir_deg": 69.0
    },
    "16": {
      "temp": 9.4,
      "precip": 0.0,
      "wind": 16.8,
      "wind_dir_deg": 52.0
    }
  },
  "ride_temp_mean": 8.35,
  "ride_wind_mean": 15.8,
  "ride_wind_dir_deg": 70.94837046901455,
  "ride_rain_flag": 1.0,
  "tent_rain_flag": 1.0,
  "daily_precip_sum": 7.4,
  "daily_temp_mean": 6.7124999999999995,
  "daily_wind_mean": 15.25,
  "daily_wind_dir_deg": 75.62000833515856
}