{
  "samples_local": {
    "10": {
      "temp": 2.5,
      "precip": 0.0,
      "wind": 7.2,
      "wind_dir_deg": 342.0
    },
    "12": {
      "temp": 6.5,
      "precip": 0.0,
      "wind": 5.2,
      "wind_dir_deg": 16.0
    },
    "14": {
      "temp": 8.9,
      "precip": 0.0,
      "wind": 6.2,
      "wind_dir_deg": 21.0
    },
    "16": {
      "temp": 9.0,
      "precip": 0.0,
      "wind": 5.4,
      "wind_dir_deg": 8.0
    }
  },
  "ride_temp_mean": 6.725,
  "ride_wind_mean": 6.0,
  "ride_wind_dir_deg": 5.423194241601891,
  "ride_rain_flag": 0.0,
  "tent_rain_flag": 0.0,
  "daily_precip_sum": 0.0,
  "daily_temp_mean": 3.733333333333333,
  "daily_wind_mean": 7.55,
  "daily_wind_dir_deg": 355.6491631623631
}