{
  "samples_local": {
    "10": {
      "temp": 19.5,
      "precip": 0.1,
      "wind": 2.3,
      "wind_dir_deg": 219.0
    },
    "12": {
      "temp": 22.0,
      "precip": 0.0,
      "wind": 1.1,
      "wind_dir_deg": 90.0
    },
    "14": {
      "temp": 23.6,
      "precip": 0.0,
      "wind": 2.3,
      "wind_dir_deg": 129.0
    },
    "16": {
      "temp": 24.2,
      "precip": 0.0,
      "wind": 6.1,
      "wind_dir_deg": 177.0
    }
  },
  "ride_temp_mean": 22.325,
  "ride_wind_mean": 2.9499999999999997,
  "ride_wind_dir_deg": 169.31788312319304,
  "ride_rain_flag": 0.0,
  "tent_rain_flag": 0.0,
  "daily_precip_sum": 0.30000000000000004,
  "daily_temp_mean": 17.6125,
  "daily_wind_mean": 4.766666666666667,
  "daily_wind_dir_deg": 197.0211687377823
}