{
  "samples_local": {
    "10": {
      "temp": 22.0,
      "precip": 0.2,
      "wind": 18.4,
      "wind_dir_deg": 79.0
    },
    "12": {
      "temp": 20.5,
      "precip": 2.2,
      "wind": 11.8,
      "wind_dir_deg": 67.0
    },
    "14": {
      "temp": 23.2,
      "precip": 0.0,
      "wind": 19.4,
      "wind_dir_deg": 100.0
    },
    "16": {
      "temp": 21.5,
      "precip": 0.1,
      "wind": 24.1,
      "wind_dir_deg": 110.0
    }
  },
  "ride_temp_mean": 21.8,
  "ride_wind_mean": 18.425,
  "ride_wind_dir_deg": 92.82695174112854,
  "ride_rain_flag": 1.0,
  "tent_rain_flag": 1.0,
  "daily_precip_sum": 2.8000000000000003,
  "daily_temp_mean": 18.787499999999998,
  "daily_wind_mean": 13.475,
  "daily_wind_dir_deg": 100.02156983014186
}