{
  "samples_local": {
    "10": {
      "temp": 15.5,
      "precip": 0.0,
      "wind": 15.5,
      "wind_dir_deg": 23.0
    },
    "12": {
      "temp": 15.7,
      "precip": 0.5,
      "wind": 15.2,
      "wind_dir_deg": 7.0
    },
    "14": {
      "temp": 16.0,
      "precip": 0.3,
      "wind": 17.0,
      "wind_dir_deg": 10.0
    },
    "16": {
      "temp": 16.1,
      "precip": 0.2,
      "wind": 13.9,
      "wind_dir_deg": 359.0
    }
  },
  "ride_temp_mean": 15.825,
  "ride_wind_mean": 15.4,
  "ride_wind_dir_deg": 10.03666628187193,
  "ride_rain_flag": 1.0,
  "tent_rain_flag": 1.0,
  "daily_precip_sum": 6.8,
  "daily_temp_mean": 14.637500000000001,
  "daily_wind_mean": 12.875,
  "daily_wind_dir_deg": 2.221365902857883
}