{"daily_oneday_rows": [{"date": "2016-05-12", "tavg": 9.4, "prcp": 5.7, "wspd": 4.9, "wdir": 286.0}, {"date": "2017-05-12", "tavg": 12.4, "prcp": 0.8, "wspd": 5.9, "wdir": 164.0}, {"date": "2018-05-12", "tavg": 9.7, "prcp": 18.7, "wspd": 13.7, "wdir": 303.0}, {"date": "2019-05-12", "tavg": 8.7, "prcp": 0.7, "wspd": 27.7, "wdir": 311.0}, {"date": "2020-05-12", "tavg": 9.3, "prcp": 0.9, "wspd": 8.0, "wdir": 18.0}, {"date": "2021-05-12", "tavg": 8.4, "prcp": 4.1, "wspd": 11.5, "wdir": 301.0}, {"date": "2022-05-12", "tavg": 16.1, "prcp": 0.0, "wspd": 6.4, "wdir": 99.0}, {"date": "2023-05-12", "tavg": 7.5, "prcp": 1.5, "wspd": 18.9, "wdir": 306.0}, {"date": "2024-05-12", "tavg": 13.3, "prcp": 2.5, "wspd": 4.3, "wdir": 316.0}, {"date": "2025-05-12", "tavg": 9.3, "prcp": 1.4, "wspd": 7.1, "wdir": 298.0}]}