{"daily_oneday_rows": [{"date": "2016-02-15", "tavg": 1.9, "prcp": 4.0, "wspd": 20.4, "wdir": 354.0}, {"date": "2017-02-15", "tavg": 7.7, "prcp": 0.0, "wspd": 8.5, "wdir": 139.0}, {"date": "2018-02-15", "tavg": 8.1, "prcp": 0.2, "wspd": 6.1, "wdir": 159.0}, {"date": "2019-02-15", "tavg": 5.0, "prcp": 0.0, "wspd": 7.8, "wdir": 124.0}, {"date": "2020-02-15", "tavg": 8.9, "prcp": 0.0, "wspd": 9.9, "wdir": 135.0}, {"date": "2021-02-15", "tavg": 6.8, "prcp": 0.0, "wspd": 16.0, "wdir": 138.0}, {"date": "2022-02-15", "tavg": 5.1, "prcp": 1.7, "wspd": 11.3, "wdir": 312.0}, {"date": "2023-02-15", "tavg": 7.5, "prcp": 0.0, "wspd": 6.5, "wdir": 147.0}, {"date": "2024-02-15", "tavg": 12.4, "prcp": 4.0, "wspd": 13.8, "wdir": 136.0}, {"date": "2025-02-15", "tavg": 7.7, "prcp": 0.0, "wspd": 7.4, "wdir": 132.0}]}