{"daily_oneday_rows": [{"date": "2016-02-14", "tavg": 5.1, "prcp": 4.0, "wspd": 16.9, "wdir": 295.0}, {"date": "2017-02-14", "tavg": 7.0, "prcp": 56.9, "wspd": 20.6, "wdir": 118.0}, {"date": "2018-02-14", "tavg": 2.0, "prcp": 2.2, "wspd": 9.9, "wdir": 316.0}, {"date": "2019-02-14", "tavg": 5.6, "prcp": 0.0, "wspd": 12.0, "wdir": 110.0}, {"date": "2020-02-14", "tavg": 6.2, "prcp": 0.0, "wspd": 19.5, "wdir": 316.0}, {"date": "2021-02-14", "tavg": 1.0, "prcp": 1.1, "wspd": 12.0, "wdir": 137.0}, {"date": "2022-02-14", "tavg": 5.7, "prcp": 4.4, "wspd": 18.9, "wdir": 304.0}, {"date": "2023-02-14", "tavg": 3.5, "prcp": 0.0, "wspd": 9.2, "wdir": 103.0}, {"date": "2024-02-14", "tavg": 9.3, "prcp": 0.0, "wspd": 8.4, "wdir": 344.0}, {"date": "2025-02-14", "tavg": 6.6, "prcp": 0.0, "wspd": 20.3, "wdir": 328.0}]}