{"daily_oneday_rows": [{"date": "2016-02-03", "tavg": 9.9, "prcp": 6.6, "wspd": 18.4, "wdir": 317.0}, {"date": "2017-02-03", "tavg": 11.6, "prcp": 2.3, "wspd": 18.0, "wdir": 190.0}, {"date": "2018-02-03", "tavg": 7.5, "prcp": 20.2, "wspd": 17.9, "wdir": 276.0}, {"date": "2019-02-03", "tavg": 5.7, "prcp": 1.5, "wspd": 8.3, "wdir": 19.0}, {"date": "2020-02-03", "tavg": 16.1, "prcp": 0.0, "wspd": 9.7, "wdir": 199.0}, {"date": "2021-02-03", "tavg": 13.8, "prcp": 0.7, "wspd": 17.2, "wdir": 187.0}, {"date": "2022-02-03", "tavg": 9.3, "prcp": 0.0, "wspd": 10.2, "wdir": 245.0}, {"date": "2023-02-03", "tavg": 4.5, "prcp": 0.0, "wspd": 7.1, "wdir": 87.0}, {"date": "2024-02-03", "tavg": 9.0, "prcp": 0.0, "wspd": 7.1, "wdir": 83.0}, {"date": "2025-02-03", "tavg": 8.8, "prcp": 0.0, "wspd": 4.5, "wdir": 219.0}]}