{"latitude": 42.003513, "longitude": 12.445415, "generationtime_ms": 5.009651184082031, "utc_offset_seconds": 0, "timezone": "GMT", "timezone_abbreviation": "GMT", "elevation": 18.0, "daily_units": {"time": "iso8601", "temperature_2m_mean": "\u00b0C", "precipitation_sum": "mm", "windspeed_10m_mean": "km/h", "winddirection_10m_dominant": "\u00b0"}, "daily": {"time": ["2016-09-15"], "temperature_2m_mean": [22.3], "precipitation_sum": [1.3], "windspeed_10m_mean": [7.5], "winddirection_10m_dominant": [157]}}