{
  "samples_local": {
    "10": {
      "temp": -0.1,
      "precip": 0.1,
      "wind": 27.8,
      "wind_dir_deg": 48.0
    },
    "12": {
      "temp": 0.6,
      "precip": 0.0,
      "wind": 24.1,
      "wind_dir_deg": 76.0
    },
    "14": {
      "temp": 0.5,
      "precip": 0.1,
      "wind": 17.4,
      "wind_dir_deg": 97.0
    },
    "16": {
      "temp": -0.7,
      "precip": 0.0,
      "wind": 8.6,
      "wind_dir_deg": 88.0
    }
  },
  "ride_temp_mean": 0.07500000000000001,
  "ride_wind_mean": 19.475,
  "ride_wind_dir_deg": 72.07633615623911,
  "ride_rain_flag": 0.0,
  "tent_rain_flag": 1.0,
  "daily_precip_sum": 4.2,
  "daily_temp_mean": -1.1208333333333333,
  "daily_wind_mean": 19.408333333333335,
  "daily_wind_dir_deg": 47.87514094501728
}