{
  "samples_local": {
    "10": {
      "temp": 6.3,
      "precip": 0.0,
      "wind": 10.2,
      "wind_dir_deg": 312.0
    },
    "12": {
      "temp": 8.1,
      "precip": 0.0,
      "wind": 10.7,
      "wind_dir_deg": 312.0
    },
    "14": {
      "temp": 9.5,
      "precip": 0.0,
      "wind": 10.2,
      "wind_dir_deg": 318.0
    },
    "16": {
      "temp": 9.5,
      "precip": 0.0,
      "wind": 8.9,
      "wind_dir_deg": 317.0
    }
  },
  "ride_temp_mean": 8.35,
  "ride_wind_mean": 10.0,
  "ride_wind_dir_deg": 314.64235134447944,
  "ride_rain_flag": 0.0,
  "tent_rain_flag": 0.0,
  "daily_precip_sum": 0.0,
  "daily_temp_mean": 6.3125,
  "daily_wind_mean": 9.641666666666667,
  "daily_wind_dir_deg": 314.2385218583612
}