{
  "samples_local": {
    "10": {
      "temp": 8.7,
      "precip": 0.0,
      "wind": 4.1,
      "wind_dir_deg": 322.0
    },
    "12": {
      "temp": 9.7,
      "precip": 0.0,
      "wind": 7.2,
      "wind_dir_deg": 342.0
    },
    "14": {
      "temp": 11.3,
      "precip": 0.2,
      "wind": 5.8,
      "wind_dir_deg": 300.0
    },
    "16": {
      "temp": 10.6,
      "precip": 0.1,
      "wind": 4.5,
      "wind_dir_deg": 284.0
    }
  },
  "ride_temp_mean": 10.075,
  "ride_wind_mean": 5.4,
  "ride_wind_dir_deg": 314.85513738826404,
  "ride_rain_flag": 1.0,
  "tent_rain_flag": 1.0,
  "daily_precip_sum": 2.3,
  "daily_temp_mean": 7.745833333333334,
  "daily_wind_mean": 7.429166666666667,
  "daily_wind_dir_deg": 359.2487327091478
}