{
  "samples_local": {
    "10": {
      "temp": 9.6,
      "precip": 0.0,
      "wind": 9.0,
      "wind_dir_deg": 5.0
    },
    "12": {
      "temp": 12.2,
      "precip": 0.0,
      "wind": 17.3,
      "wind_dir_deg": 48.0
    },
    "14": {
      "temp": 11.7,
      "precip": 0.1,
      "wind": 9.0,
      "wind_dir_deg": 37.0
    },
    "16": {
      "temp": 11.8,
      "precip": 0.0,
      "wind": 10.5,
      "wind_dir_deg": 31.0
    }
  },
  "ride_temp_mean": 11.325,
  "ride_wind_mean": 11.45,
  "ride_wind_dir_deg": 33.66693248244462,
  "ride_rain_flag": 0.0,
  "tent_rain_flag": 1.0,
  "daily_precip_sum": 1.8,
  "daily_temp_mean": 8.3125,
  "daily_wind_mean": 12.458333333333334,
  "daily_wind_dir_deg": 35.26080679968919
}