{
  "samples_local": {
    "10": {
      "temp": 2.8,
      "precip": 0.0,
      "wind": 15.7,
      "wind_dir_deg": 90.0
    },
    "12": {
      "temp": 4.8,
      "precip": 0.0,
      "wind": 18.1,
      "wind_dir_deg": 99.0
    },
    "14": {
      "temp": 3.8,
      "precip": 0.0,
      "wind": 12.5,
      "wind_dir_deg": 83.0
    },
    "16": {
      "temp": 3.8,
      "precip": 0.0,
      "wind": 11.7,
      "wind_dir_deg": 86.0
    }
  },
  "ride_temp_mean": 3.8,
  "ride_wind_mean": 14.5,
  "ride_wind_dir_deg": 90.4888652238239,
  "ride_rain_flag": 0.0,
  "tent_rain_flag": 0.0,
  "daily_precip_sum": 0.0,
  "daily_temp_mean": 1.5374999999999999,
  "daily_wind_mean": 12.479166666666666,
  "daily_wind_dir_deg": 82.49410077019161
}