{
  "samples_local": {
    "10": {
      "temp": 9.8,
      "precip": 0.0,
      "wind": 5.8,
      "wind_dir_deg": 106.0
    },
    "12": {
      "temp": 12.0,
      "precip": 0.0,
      "wind": 8.8,
      "wind_dir_deg": 88.0
    },
    "14": {
      "temp": 12.8,
      "precip": 0.0,
      "wind": 13.9,
      "wind_dir_deg": 119.0
    },
    "16": {
      "temp": 12.8,
      "precip": 0.0,
      "wind": 15.6,
      "wind_dir_deg": 128.0
    }
  },
  "ride_temp_mean": 11.850000000000001,
  "ride_wind_mean": 11.025,
  "ride_wind_dir_deg": 114.43078709865597,
  "ride_rain_flag": 0.0,
  "tent_rain_flag": 0.0,
  "daily_precip_sum": 0.0,
  "daily_temp_mean": 8.3,
  "daily_wind_mean": 8.004166666666666,
  "daily_wind_dir_deg": 111.48333768137138
}