{
  "samples_local": {
    "10": {
      "temp": 9.4,
      "precip": 0.0,
      "wind": 27.4,
      "wind_dir_deg": 348.0
    },
    "12": {
      "temp": 10.0,
      "precip": 0.0,
      "wind": 30.6,
      "wind_dir_deg": 345.0
    },
    "14": {
      "temp": 10.7,
      "precip": 0.1,
      "wind": 29.4,
      "wind_dir_deg": 342.0
    },
    "16": {
      "temp": 10.2,
      "precip": 0.2,
      "wind": 31.7,
      "wind_dir_deg": 346.0
    }
  },
  "ride_temp_mean": 10.075,
  "ride_wind_mean": 29.775,
  "ride_wind_dir_deg": 345.2159434279251,
  "ride_rain_flag": 1.0,
  "tent_rain_flag": 1.0,
  "daily_precip_sum": 3.2,
  "daily_temp_mean": 8.25,
  "daily_wind_mean": 23.433333333333334,
  "daily_wind_dir_deg": 353.68283567786165
}