{
  "samples_local": {
    "10": {
      "temp": 12.4,
      "precip": 0.0,
      "wind": 8.7,
      "wind_dir_deg": 232.0
    },
    "12": {
      "temp": 13.7,
      "precip": 0.0,
      "wind": 6.8,
      "wind_dir_deg": 220.0
    },
    "14": {
      "temp": 13.9,
      "precip": 0.0,
      "wind": 6.6,
      "wind_dir_deg": 191.0
    },
    "16": {
      "temp": 13.3,
      "precip": 0.0,
      "wind": 6.4,
      "wind_dir_deg": 190.0
    }
  },
  "ride_temp_mean": 13.325,
  "ride_wind_mean": 7.125,
  "ride_wind_dir_deg": 210.21674566207753,
  "ride_rain_flag": 0.0,
  "tent_rain_flag": 0.0,
  "daily_precip_sum": 0.1,
  "daily_temp_mean": 10.200000000000001,
  "daily_wind_mean": 5.854166666666667,
  "daily_wind_dir_deg": 191.20821188232847
}