{
  "samples_local": {
    "10": {
      "temp": 4.0,
      "precip": 0.0,
      "wind": 3.2,
      "wind_dir_deg": 223.0
    },
    "12": {
      "temp": 9.1,
      "precip": 0.0,
      "wind": 3.7,
      "wind_dir_deg": 39.0
    },
    "14": {
      "temp": 8.3,
      "precip": 0.0,
      "wind": 6.7,
      "wind_dir_deg": 38.0
    },
    "16": {
      "temp": 5.3,
      "precip": 0.0,
      "wind": 3.3,
      "wind_dir_deg": 22.0
    }
  },
  "ride_temp_mean": 6.675,
  "ride_wind_mean": 4.225,
  "ride_wind_dir_deg": 31.822422429951587,
  "ride_rain_flag": 0.0,
  "tent_rain_flag": 0.0,
  "daily_precip_sum": 0.0,
  "daily_temp_mean": 1.5583333333333333,
  "daily_wind_mean": 3.9291666666666667,
  "daily_wind_dir_deg": 222.8682311855781
}